Workbook

Sheet Combined Ledger
A1: COMBINED LEDGER - Raja, Santhu & Annadhanam
A3: TOTAL INCOME | C3: =C93 -> 259268 | E3: TOTAL EXPENDITURE | G3: =G93 -> 181120
A4: NET BALANCE = TOTAL INCOME − TOTAL EXPENDITURE | G4: =C3-G3 -> 78148
A6: INCOME | E6: EXPENDITURE
A7: S.No | B7: Particulars | C7: Amount (Rs.) | E7: S.No | F7: Particulars | G7: Amount (Rs.)
A8: 1 | B8: last year balance | C8: 22000 | E8: 1 | F8: stationary | G8: 200
A9: 2 | B9: last year balance | C9: 10000 | E9: 2 | F9: vamsi lighting | G9: 6000
A10: 3 | B10: kumari mam | C10: 1000 | E10: 3 | F10: (no description in source) | G10: 2000
A11: 4 | B11: raja | C11: 2500 | E11: 4 | F11: small poola mala | G11: 350
A12: 5 | B12: tarun | C12: 2500 | E12: 5 | F12: colours | G12: 200
A13: 6 | B13: ravi | C13: 2500 | E13: 6 | F13: police | G13: 1000
A14: 7 | B14: sampath | C14: 2500 | E14: 7 | F14: vamsi lighting | G14: 9000
A15: 8 | B15: venu annaya | C15: 2500 | E15: 8 | F15: (no description in source) | G15: 300
A16: 9 | B16: karthik | C16: 1000 | E16: 9 | F16: (no description in source) | G16: 240
A17: 10 | B17: vinay | C17: 4000 | E17: 10 | F17: vamsi lighting | G17: 15000
A18: 11 | B18: hemant ch | C18: 2500 | E18: 11 | F18: (no description in source) | G18: 200
A19: 12 | B19: sai syam | C19: 1000 | E19: 12 | F19: police | G19: 1000
... A80: 73 | B80: kranthi | C80: 2000 | E80: 73 | F80: van | G80: 4000
A81: 74 | B81: sashi | C81: 10000
A82: 75 | B82: anand | C82: 2000
A83: 76 | B83: samba | C83: 6000
A84: 77 | B84: vasanti | C84: 5000
A85: 78 | B85: maddi sruinu | C85: 5000
A86: 79 | B86: avinash | C86: 1800
A87: 80 | B87: bhavitha | C87: 1000
A88: 81 | B88: d appalareddyy | C88: 1000
A89: 82 | B89: panda seenu | C89: 2000
A90: 83 | B90: hemanth maddi | C90: 2500
A91: 84 | B91: dumpa poli | C91: 5000
A92: 85 | B92: nagaraju | C92: 10000
B93: TOTAL INCOME | C93: =SUM(C8:C92) -> 259268 | F93: TOTAL EXPENDITURE | G93: =SUM(G8:G92) -> 181120
B95: NET BALANCE (INCOME − EXPENDITURE) | C95: =C93-G93 -> 78148
A97: Check vs. original "Final Total" sheet: | E97: =IF(AND(C93='Final Total'!B8,G93='Final Total'!C8,C95='Final Total'!D8),"OK - income, expenditure & net all match","MISMATCH - please review") -> OK - income, expenditure & net all match

Sheet Raja
A1: RAJA - LEDGER
A3: INCOME
A4: S.No | B4: Particulars | C4: Amount (Rs.)
A5: 1 | B5: last year balance | C5: 22000
A6: 2 | B6: last year balance | C6: 10000
A7: 3 | B7: kumari mam | C7: 1000
A8: 4 | B8: raja | C8: 2500
A9: 5 | B9: tarun | C9: 2500
A10: 6 | B10: ravi | C10: 2500
A11: 7 | B11: sampath | C11: 2500
A12: 8 | B12: venu annaya | C12: 2500
A13: 9 | B13: karthik | C13: 1000
A14: 10 | B14: vinay | C14: 4000
A15: 11 | B15: hemant ch | C15: 2500
A16: 12 | B16: sai syam | C16: 1000
... A28: 24 | B28: vamsi amount | C28: 2500
B29: TOTAL INCOME | C29: =SUM(C5:C28) -> 96500
A31: EXPENDITURE
A32: S.No | B32: Particulars | C32: Amount (Rs.)
A33: 1 | B33: stationary | C33: 200
A34: 2 | B34: vamsi lighting | C34: 6000
A35: 3 | B35: (no description in source) | C35: 2000
A36: 4 | B36: small poola mala | C36: 350
A37: 5 | B37: colours | C37: 200
A38: 6 | B38: police | C38: 1000
A39: 7 | B39: vamsi lighting | C39: 9000
A40: 8 | B40: (no description in source) | C40: 300
A41: 9 | B41: (no description in source) | C41: 240
A42: 10 | B42: vamsi lighting | C42: 15000
A43: 11 | B43: (no description in source) | C43: 200
A44: 12 | B44: police | C44: 1000
... A57: 25 | B57: petrol | C57: 1000
B58: TOTAL EXPENDITURE | C58: =SUM(C33:C57) -> 60390
B60: NET (RAJA) = INCOME − EXPENDITURE | C60: =C29-C58 -> 36110

Sheet Santhu
A1: SANTHU - LEDGER
A3: INCOME
A4: S.No | B4: Particulars | C4: Amount (Rs.)
A5: 1 | B5: last year balance | C5: 3000
A6: 2 | B6: polamamba aamount | C6: 800
A7: 3 | B7: last year balance | C7: 15000
A8: 4 | B8: 1st sep chanda book | C8: 1001
A9: 5 | B9: 2nd sep chanda book | C9: 501
A10: 6 | B10: 3rd sep chanda book | C10: 3200
A11: 7 | B11: 5th sep chanda book | C11: 1000
A12: 8 | B12: 6th sep chanda book | C12: 2200
A13: 9 | B13: 7th sep chanda book | C13: 1000
A14: 10 | B14: karthik | C14: 1500
A15: 11 | B15: kumar | C15: 1500
A16: 12 | B16: siva annaya | C16: 2500
... A49: 45 | B49: venkatesh | C49: 7000
B50: TOTAL INCOME | C50: =SUM(C5:C49) -> 100918
A52: EXPENDITURE
A53: S.No | B53: Particulars | C53: Amount (Rs.)
A54: 1 | B54: dj | C54: 2000
A55: 2 | B55: banner | C55: 800
A56: 3 | B56: k vamsi | C56: 1500
A57: 4 | B57: k vamsi | C57: 13000
A58: 5 | B58: elec | C58: 500
A59: 6 | B59: small banner | C59: 250
A60: 7 | B60: panthulu | C60: 1000
A61: 8 | B61: coconuts | C61: 1200
A62: 9 | B62: sweets | C62: 150
A63: 10 | B63: t shirts | C63: 4000
A64: 11 | B64: riksahw | C64: 200
A65: 12 | B65: water | C65: 200
... A95: 42 | B95: kolatam | C95: 6000
B96: TOTAL EXPENDITURE | C96: =SUM(C54:C95) -> 90800
B98: NET (SANTHU) = INCOME − EXPENDITURE | C98: =C50-C96 -> 10118

Sheet Annadhanam
A1: ANNADHANAM - LEDGER
A3: INCOME
A4: S.No | B4: Particulars | C4: Amount (Rs.)
A5: 1 | B5: tata | C5: 1750
A6: 2 | B6: boya | C6: 5000
A7: 3 | B7: pm | C7: 1800
A8: 4 | B8: kranthi | C8: 2000
A9: 5 | B9: sashi | C9: 10000
A10: 6 | B10: anand | C10: 2000
A11: 7 | B11: samba | C11: 6000
A12: 8 | B12: vasanti | C12: 5000
A13: 9 | B13: maddi sruinu | C13: 5000
A14: 10 | B14: avinash | C14: 1800
A15: 11 | B15: bhavitha | C15: 1000
A16: 12 | B16: d appalareddyy | C16: 1000
... A20: 16 | B20: nagaraju | C20: 10000
B21: TOTAL INCOME | C21: =SUM(C5:C20) -> 61850
A23: EXPENDITURE
A24: S.No | B24: Particulars | C24: Amount (Rs.)
A25: 1 | B25: anand maya | C25: 14000
A26: 2 | B26: anand maya | C26: 10000
A27: 3 | B27: ladoo | C27: 750
A28: 4 | B28: nimmakayalu and coconuts | C28: 1000
A29: 5 | B29: pramidalu | C29: 180
A30: 6 | B30: van | C30: 4000
B31: TOTAL EXPENDITURE | C31: =SUM(C25:C30) -> 29930
B33: NET (ANNADHANAM) = INCOME − EXPENDITURE | C33: =C21-C31 -> 31920

Sheet Final Total
A1: Final Total - Raja, Santhu & Annadhanam
A3: Ledger | B3: Total Income (Rs.) | C3: Total Expenditure (Rs.) | D3: Net (Rs.)
A4: Raja | B4: =Raja!C29 -> 96500 | C4: =Raja!C58 -> 60390 | D4: =B4-C4 -> 36110
A5: Santhu | B5: =Santhu!C50 -> 100918 | C5: =Santhu!C96 -> 90800 | D5: =B5-C5 -> 10118
A6: Annadhanam | B6: =Annadhanam!C21 -> 61850 | C6: =Annadhanam!C31 -> 29930 | D6: =B6-C6 -> 31920
A7: RAJA + SANTHU (combined) | B7: =B4+B5 -> 197418 | C7: =C4+C5 -> 151190 | D7: =D4+D5 -> 46228
A8: GRAND TOTAL (Raja + Santhu + Annadhanam) | B8: =B4+B5+B6 -> 259268 | C8: =C4+C5+C6 -> 181120 | D8: =D4+D5+D6 -> 78148
A10: Note: Figures taken directly from the separately-uploaded Raja, Santhu and Annadhanam ledger sheets. Raja's total (Rs. 36,110) matches the check total printed at the bottom of that source sheet.
